angr_zelos_target/__init__.py
angr_zelos_target/angr_zelos_target.py
angr_zelos_target/example/__main__.py
angr_zelos_target/example/not_packed_elf64
angr_zelos_target-0.0.1.dist-info/LICENSE
angr_zelos_target-0.0.1.dist-info/METADATA
angr_zelos_target-0.0.1.dist-info/WHEEL
angr_zelos_target-0.0.1.dist-info/top_level.txt
angr_zelos_target-0.0.1.dist-info/RECORD
