Metadata-Version: 2.1
Name: angr-zelos-target
Version: 0.0.1
Summary: Zelos target for angr / symbion concrete execution.
Home-page: https://github.com/zeropointdynamics/angr_zelos_target
Author: Zeropoint Dynamics
Author-email: zelos@zeropointdynamics.com
Maintainer: Zeropoint Dynamics
Maintainer-email: zelos@zeropointdynamics.com
License: AGPLv3
Project-URL: Documentation, https://zelos.zeropointdynamics.com/
Project-URL: Bug Tracker, https://github.com/zeropointdynamics/angr_zelos_target/issues
Project-URL: Source Code, https://github.com/zeropointdynamics/angr_zelos_target
Keywords: emulation,dynamic analysis,binary analysis,symbolic execution
Platform: UNKNOWN
Classifier: Development Status :: 4 - Beta
Classifier: Natural Language :: English
Classifier: License :: OSI Approved :: GNU Affero General Public License v3
Classifier: Operating System :: OS Independent
Classifier: Programming Language :: Python
Classifier: Programming Language :: Python :: 3
Classifier: Programming Language :: Python :: 3.6
Classifier: Programming Language :: Python :: 3.7
Classifier: Programming Language :: Python :: 3.8
Requires-Python: >=3.6.0
Requires-Dist: wheel
